<?xml version="1.0" encoding="iso-8859-1" ?>
<newsitem itemid="478583" id="root" date="1997-04-01" xml:lang="en">
<title>ALBANIA: States pledge troops for Albania security force.</title>
<headline>States pledge troops for Albania security force.</headline>
<dateline>TIRANA 1997-04-01</dateline>
<text>
<p>The following is a list of the countries which have offered troops so far to the Italian-led multinational force which is due to be deployed in Albania to protect humanitarian relief operations:</p>
<p>-- Italy, which will organise and lead the force, is expected to provide 2,000 to 2,500 troops</p>
<p>-- France, 1,000 troops plus armoured cars and armoured personnel carriers</p>
<p>-- Greece,  700 troops</p>
<p>-- Turkey,  500 troops</p>
<p> -- Spain,   500 troops</p>
<p>-- Romania, 400 troops</p>
<p>The 5,000-strong force will be deployed at Tirana airport, the Adriatic ports of Durres and Vlore, and will protect relief convoys around the country.</p>
<p>Diplomats said 2,500 troops were expected to be deployed initially and 2,500 would be held in reserve.</p>
</text>
<copyright>(c) Reuters Limited 1997</copyright>
<metadata>
<codes class="bip:countries:1.0">
  <code code="ALB">
    <editdetail attribution="Reuters BIP Coding Group" action="confirmed" date="1997-04-01"/>
  </code>
  <code code="FRA">
    <editdetail attribution="Reuters BIP Coding Group" action="confirmed" date="1997-04-01"/>
  </code>
  <code code="GREECE">
    <editdetail attribution="Reuters BIP Coding Group" action="confirmed" date="1997-04-01"/>
  </code>
  <code code="ITALY">
    <editdetail attribution="Reuters BIP Coding Group" action="confirmed" date="1997-04-01"/>
  </code>
  <code code="ROM">
    <editdetail attribution="Reuters BIP Coding Group" action="confirmed" date="1997-04-01"/>
  </code>
  <code code="SPAIN">
    <editdetail attribution="Reuters BIP Coding Group" action="confirmed" date="1997-04-01"/>
  </code>
  <code code="TURK">
    <editdetail attribution="Reuters BIP Coding Group" action="confirmed" date="1997-04-01"/>
  </code>
</codes>
<codes class="bip:topics:1.0">
  <code code="GCAT">
    <editdetail attribution="Reuters BIP Coding Group" action="confirmed" date="1997-04-01"/>
  </code>
  <code code="GDIP">
    <editdetail attribution="Reuters BIP Coding Group" action="confirmed" date="1997-04-01"/>
  </code>
  <code code="GVIO">
    <editdetail attribution="Reuters BIP Coding Group" action="confirmed" date="1997-04-01"/>
  </code>
</codes>
<dc element="dc.date.created" value="1997-04-01"/>
<dc element="dc.publisher" value="Reuters Holdings Plc"/>
<dc element="dc.date.published" value="1997-04-01"/>
<dc element="dc.source" value="Reuters"/>
<dc element="dc.creator.location" value="TIRANA"/>
<dc element="dc.creator.location.country.name" value="ALBANIA"/>
<dc element="dc.source" value="Reuters"/>
</metadata>
</newsitem>
