<?xml version="1.0" encoding="iso-8859-1" ?>
<newsitem itemid="480481" id="root" date="1997-04-01" xml:lang="en">
<title>TAIWAN: PRESS DIGEST - Taiwan newspapers - April 1.</title>
<headline>PRESS DIGEST - Taiwan newspapers - April 1.</headline>
<dateline>TAIPEI 1997-04-01</dateline>
<text>
<p>These are the leading stories in the Taiwan press on Tuesday. Reuters has not verified these stories and does not vouch for their accuracy.</p>
<p>Newspaper headlines</p>
<p>CHINA TIMES - Formosa Chairman Wang Yung-ching says Formosa has not yet financed any investment in China power plant.</p>
<p>Fang Yuan township head Chen Chu-tsan detained on charges of corruption.</p>
<p>UNITED DAILY NEWS - Formosa to drop China power plant project if government disapproves.</p>
<p>Central bank governor Sheu Yuan-dong to open inquiry to check flow of Taiwan funds into mainland China.</p>
<p>LIBERTY TIMES - Wang Yung-ching to abandon China power plant.</p>
<p>Wu Shih-wen to become navy commander-in-chief.</p>
<p>COMMERCIAL TIMES - Formosa chairman Wang Yung-Ching and Economic Minister Wang Chih-kang meet, reach agreement on Formosa's investment in Fujian power station.</p>
<p>Central bank officials admit it difficult to chase bid-capital businesses' fund flows.</p>
<p>ECONOMIC DAILY NEWS - Wall Street plunges.</p>
<p>Foreign stocks can be traded in Taiwan in July.</p>
<p>-- Taipei Newsroom (5080815)</p>
</text>
<copyright>(c) Reuters Limited 1997</copyright>
<metadata>
<codes class="bip:countries:1.0">
  <code code="TAIWAN">
    <editdetail attribution="Reuters BIP Coding Group" action="confirmed" date="1997-04-01"/>
  </code>
</codes>
<codes class="bip:topics:1.0">
  <code code="GCAT">
    <editdetail attribution="Reuters BIP Coding Group" action="confirmed" date="1997-04-01"/>
  </code>
</codes>
<dc element="dc.date.created" value="1997-04-01"/>
<dc element="dc.publisher" value="Reuters Holdings Plc"/>
<dc element="dc.date.published" value="1997-04-01"/>
<dc element="dc.source" value="Reuters"/>
<dc element="dc.creator.location" value="TAIPEI"/>
<dc element="dc.creator.location.country.name" value="TAIWAN"/>
<dc element="dc.source" value="Reuters"/>
</metadata>
</newsitem>
