<?xml version="1.0" encoding="iso-8859-1" ?>
<newsitem itemid="569335" id="root" date="1997-05-08" xml:lang="en">
<title>INDONESIA: Indonesia Key Economic Indicators.</title>
<headline>Indonesia Key Economic Indicators.</headline>
<text>
<p>==================================</p>
<p>--------------------------------------------------------------</p>
<p> Indicator	   Period  Latest     Prev   Yr-Ago     Yr-Yr</p>
<p>--------------------------------------------------------------</p>
<p> GDP	    Pct  Annual  7.82(96) 8.21(95)  7.48(94) 6.7 (93)</p>
<p>--------------------------------------------------------------</p>
<p> CPI	    Pct     Apr   +0.56    -0.12    +0.78     4.95</p>
<p>--------------------------------------------------------------</p>
<p> Exports	$Bln    Feb    4.06     4.24     3.69	-</p>
<p>--------------------------------------------------------------</p>
<p> Imports	$Bln    Feb    3.09     3.67     2.87	-</p>
<p>--------------------------------------------------------------</p>
<p>Current A/C  $Bln  Annual -7.51(95) -3.7(94) -3.2(93) -2.9(92)</p>
<p>--------------------------------------------------------------</p>
<p> M2     y/y in pct    Mar   26.7     28.6     28.0</p>
<p>--------------------------------------------------------------</p>
<p> M1     y/y in pct    Mar   19.6     20.4     18.0</p>
<p>--------------------------------------------------------------</p>
<p> Bank loans   Rp-Trn  Dec  292.00   281.99   234.61	n/a</p>
<p>--------------------------------------------------------------</p>
<p> Rupiah/USD*	  May 07  2,429.60 2,424.80  2,326.75   n/a</p>
<p>--------------------------------------------------------------</p>
<p> Foreign Reserves $Bln Mar 19.872   19.862    15.975    n/a</p>
<p>--------------------------------------------------------------</p>
<p> JSE Index	    May 07  666.84  659.60    613.84	n/a</p>
<p>--------------------------------------------------------------</p>
<p>*Middle rate</p>
</text>
<copyright>(c) Reuters Limited 1997</copyright>
<metadata>
<codes class="bip:countries:1.0">
  <code code="INDON">
    <editdetail attribution="Reuters BIP Coding Group" action="confirmed" date="1997-05-08"/>
  </code>
</codes>
<codes class="bip:topics:1.0">
  <code code="E71">
    <editdetail attribution="Reuters BIP Coding Group" action="confirmed" date="1997-05-08"/>
  </code>
  <code code="ECAT">
    <editdetail attribution="Reuters BIP Coding Group" action="confirmed" date="1997-05-08"/>
  </code>
</codes>
<dc element="dc.publisher" value="Reuters Holdings Plc"/>
<dc element="dc.date.published" value="1997-05-08"/>
<dc element="dc.source" value="Reuters"/>
<dc element="dc.creator.location.country.name" value="INDONESIA"/>
<dc element="dc.source" value="Reuters"/>
</metadata>
</newsitem>
