<?xml version="1.0" encoding="iso-8859-1" ?>
<newsitem itemid="569569" id="root" date="1997-05-08" xml:lang="en">
<title>USA: Dodge City feeder steer prices mixed - USDA.</title>
<headline>Dodge City feeder steer prices mixed - USDA.</headline>
<dateline>DODGE CITY 1997-05-08</dateline>
<text>
<p>Feeder steers 300-600 lbs in a limited supply $3.00-$5.00 per cwt lower; 600-750 lbs $1.00-$2.00 higher; 750-950 lbs $3.00-$6.00 higher, compared with last week, USDA said. Feeder heifers 300-500 lbs steady to $1.00 higher; 500-600 lbs $1.00- $3.00 lower; 600-800 lbs $1.00-$3.00 higher; few 800-850 lbs $4.00-$6.00 higher. Trade active, demand very good. Receipts 76 percent 600 lbs and over; 17 percent 600 lbs and under; 07 percent cows and bulls with 350 early.</p>
<p>Feeder Steers - (Figures in parentheses are weighted average prices) Medium and Large 1 600-650 lbs 79.00-81.00 (80.26); 650-700 lbs 75.00-81.60 (79.04); 700-750 lbs 75.50-79.00 (77.17); 750-800 lbs 73.00-77.75 (76.05); 800-850 lbs 73.00-77.85 (75.50); 850-900 lbs 72.00-76.30 (74.34); 12 head 957 lbs 70.50. Full and/or fleshy 14 head 640 lbs 74.50; 650-700 lbs 74.00-74.50 (74.29). Medium and Large 1-2 450-500 lbs 79.00-85.50 (82.87); 14 head 695 lbs 73.50; 750- 800 lbs 68.50-70.50 (70.06); 25 head 810 lbs 71.75.</p>
<p>Feeder Heifers Medium and Large 1 600-650 lbs 74.25-78.75 (76.22); 650-700 lbs 72.10-75.50 (73.82); 700-750 lbs 71.75-74.25 (73.03); 750-800 lbs 70.50-73.00 (71.89); 800-850 lbs 70.10-72.60 (71.38). Full and/or fleshy 21 head 698 lbs 59.70; 17 head 716 lbs 64.25; 750-800 lbs 65.25-69.25 (66.98).</p>
<p>Medium and Large 1-2 600- 650 lbs 70.50-73.30 (72.57); 650-700 lbs 66.50-70.50 (69.79); 21 head 721 lbs 71.00. Medium 1 17 head 711 lbs 71.00.</p>
<p>Receipts - 4,868   Last Week - 3,664   Last Year - 3,178</p>
<p>((Chicago newsdesk 312-408-8720))</p>
</text>
<copyright>(c) Reuters Limited 1997</copyright>
<metadata>
<codes class="bip:countries:1.0">
  <code code="USA">
    <editdetail attribution="Reuters BIP Coding Group" action="confirmed" date="1997-05-08"/>
  </code>
</codes>
<codes class="bip:topics:1.0">
  <code code="M14">
    <editdetail attribution="Reuters BIP Coding Group" action="confirmed" date="1997-05-08"/>
  </code>
  <code code="M141">
    <editdetail attribution="Reuters BIP Coding Group" action="confirmed" date="1997-05-08"/>
  </code>
  <code code="MCAT">
    <editdetail attribution="Reuters BIP Coding Group" action="confirmed" date="1997-05-08"/>
  </code>
</codes>
<dc element="dc.date.created" value="1997-05-08"/>
<dc element="dc.publisher" value="Reuters Holdings Plc"/>
<dc element="dc.date.published" value="1997-05-08"/>
<dc element="dc.source" value="Reuters"/>
<dc element="dc.creator.location" value="DODGE CITY"/>
<dc element="dc.creator.location.country.name" value="USA"/>
<dc element="dc.source" value="Reuters"/>
</metadata>
</newsitem>
