<?xml version="1.0" encoding="iso-8859-1" ?>
<newsitem itemid="608428" id="root" date="1997-05-23" xml:lang="en">
<title>FRANCE: SOCCER-FRENCH FIRST DIVISION STANDINGS.</title>
<headline>SOCCER-FRENCH FIRST DIVISION STANDINGS.</headline>
<dateline>PARIS 1997-05-23</dateline>
<text>
<p>Standings in the French first</p>
<p>division championship before Saturday's matches:</p>
<p>				   P   W  D  L   F  A  Pts</p>
<p>  1.Monaco (champions)    37  22 10  5  67  29  76</p>
<p>  2.Nantes		    37  16 16  5  60  30  64</p>
<p>  3.Paris St Germain	37  17 13  7  55  30  64</p>
<p>  4.Bordeaux		  37  15 15  7  57  41  60</p>
<p>  5.Strasbourg		37  19  3 15  51  47  60</p>
<p>  6.Metz			37  16 11 10  39  30  59</p>
<p>  7.Auxerre		   37  16 10 11  46  31  58</p>
<p>  8.Bastia		    37  16 10 11  51  46  58</p>
<p>  9.Lyon			37  15 12 10  51  50  57</p>
<p> 10.Marseille		 37  12 13 12  43  40  49</p>
<p> 11.Montpellier	     37  11 15 11  39  40  48</p>
<p> 12.Guingamp		  37  11 13 13  32  35  46</p>
<p> 13.Lens			37  12  8 17  40  52  44</p>
<p> 14.Le Havre		  37  10 13 14  33  41  43</p>
<p> 15.Cannes		    37   9 14 14  25  40  41</p>
<p> 16.Rennes		    37  10 10 17  39  55  40</p>
<p> 17.Caen			37   7 15 15  35  46  36</p>
<p> 18.Lille		     37   8 11 18  32  57  35</p>
<p> 19.Nancy		     37   8 10 19  32  51  34</p>
<p> 20.Nice			37   5  8 24  29  65  23</p>
<p>(Note: Champions Monaco and team finishing second qualify</p>
<p>for European Cup, next best three plus League Cup winners</p>
<p>Strasbourg go into UEFA Cup, bottom four relegated).</p>
</text>
<copyright>(c) Reuters Limited 1997</copyright>
<metadata>
<codes class="bip:countries:1.0">
  <code code="FRA">
    <editdetail attribution="Reuters BIP Coding Group" action="confirmed" date="1997-05-23"/>
  </code>
  <code code="MONAC">
    <editdetail attribution="Reuters BIP Coding Group" action="confirmed" date="1997-05-23"/>
  </code>
</codes>
<codes class="bip:topics:1.0">
  <code code="GCAT">
    <editdetail attribution="Reuters BIP Coding Group" action="confirmed" date="1997-05-23"/>
  </code>
  <code code="GSPO">
    <editdetail attribution="Reuters BIP Coding Group" action="confirmed" date="1997-05-23"/>
  </code>
</codes>
<dc element="dc.date.created" value="1997-05-23"/>
<dc element="dc.publisher" value="Reuters Holdings Plc"/>
<dc element="dc.date.published" value="1997-05-23"/>
<dc element="dc.source" value="Reuters"/>
<dc element="dc.creator.location" value="PARIS"/>
<dc element="dc.creator.location.country.name" value="FRANCE"/>
<dc element="dc.source" value="Reuters"/>
</metadata>
</newsitem>
